CLUMP/ExtractSurface.py
CLUMP/GenerateClump_Euclidean_3D.py
CLUMP/GenerateClump_Favier.py
CLUMP/GenerateClump_Ferellec_McDowell.py
CLUMP/__init__.py
CLUMP/examples/Example_Euclidean_3D.py
CLUMP/examples/Example_Euclidean_3D_Extended.py
CLUMP/examples/Example_ExtractSurface.py
CLUMP/examples/Example_Favier.py
CLUMP/examples/Example_Ferellec_McDowell.py
CLUMP/examples/__init__.py
CLUMP/examples/ParticleGeometries/Binary_3D_Cube.mat
CLUMP/examples/ParticleGeometries/Binary_3D_Cuboid.mat
CLUMP/examples/ParticleGeometries/Ellipsoid_R_2.0_1.0_1.0.stl
CLUMP/examples/ParticleGeometries/Hexahedron.stl
CLUMP/examples/ParticleGeometries/Human_femur.stl
CLUMP/examples/ParticleGeometries/Octahedron.stl
CLUMP/examples/ParticleGeometries/Torus.stl
CLUMP/examples/ParticleGeometries/__init__.py
CLUMP/utils/MyRobustCrust.py
CLUMP/utils/ParticlePlotter.py
CLUMP/utils/PatchNormals.py
CLUMP/utils/RigidBodyParameters.py
CLUMP/utils/STL_ReaderWriter.py
CLUMP/utils/VTK_Writer.py
CLUMP/utils/__init__.py
clump_python-0.3.3.dist-info/LICENSE
clump_python-0.3.3.dist-info/METADATA
clump_python-0.3.3.dist-info/WHEEL
clump_python-0.3.3.dist-info/top_level.txt
clump_python-0.3.3.dist-info/RECORD
